orruns/__init__.py
orruns/decorators.py
orruns/errors.py
orruns/tracker.py
orruns/api/__init__.py
orruns/api/experiment.py
orruns/cli/__init__.py
orruns/cli/commands.py
orruns/core/__init__.py
orruns/core/config.py
orruns/utils/__init__.py
orruns/utils/error_handlers.py
orruns/utils/utils.py
orruns/visualization/__init__.py
orruns/visualization/dashboard.py
orruns/visualization/plots.py
test/__init__.py
test/test_api.py
test/test_cli.py
test/test_complex_scenarios.py
test/test_compression.py
test/test_tracker.py
test/test_visualization.py
orruns-0.1.5.dist-info/LICENSE
orruns-0.1.5.dist-info/METADATA
orruns-0.1.5.dist-info/WHEEL
orruns-0.1.5.dist-info/entry_points.txt
orruns-0.1.5.dist-info/top_level.txt
orruns-0.1.5.dist-info/RECORD
