Metadata-Version: 2.1
Name: orruns
Version: 0.1.5
Summary: Next-generation Experiment Management Platform for Operations Research
Home-page: https://github.com/lengff123/ORruns
License: GNU Affero General Public License v3
Project-URL: Bug Tracker, https://github.com/lengff123/ORruns/issues
Project-URL: Documentation, https://orruns.readthedocs.io
Project-URL: Source Code, https://github.com/lengff123/ORruns
Keywords: operations research,optimization,experiment tracking,scientific computing,mathematical optimization,research tools,experiment management,reproducible research
Platform: any
Classifier: Development Status :: 3 - Alpha
Classifier: Intended Audience :: Science/Research
Classifier: Intended Audience :: Education
Classifier: Topic :: Scientific/Engineering :: Mathematics
Classifier: Topic :: Scientific/Engineering :: Artificial Intelligence
Classifier: Topic :: Scientific/Engineering :: Information Analysis
Classifier: Programming Language :: Python :: 3 :: Only
Classifier: Programming Language :: Python :: 3.8
Classifier: Programming Language :: Python :: 3.9
Classifier: Programming Language :: Python :: 3.10
Classifier: Programming Language :: Python :: 3.11
Classifier: License :: OSI Approved :: GNU Affero General Public License v3
Classifier: Operating System :: OS Independent
Classifier: Natural Language :: English
Classifier: Environment :: Console
Requires-Python: >=3.8
License-File: LICENSE
Requires-Dist: click>=7.0
Requires-Dist: cloudpickle>=1.6.0
Requires-Dist: matplotlib>=3.3.0
Requires-Dist: numpy>=1.19.0
Requires-Dist: pandas>=1.0.0
Requires-Dist: tabulate>=0.8.0
Requires-Dist: dash
Requires-Dist: dash-bootstrap-components
Requires-Dist: plotly
Requires-Dist: flask
Provides-Extra: dev
Requires-Dist: pytest>=6.0.0; extra == "dev"
Requires-Dist: pytest-cov>=2.0.0; extra == "dev"
Requires-Dist: black>=22.0.0; extra == "dev"
Requires-Dist: isort>=5.0.0; extra == "dev"
Requires-Dist: mypy>=0.900; extra == "dev"
Requires-Dist: pylint>=2.0.0; extra == "dev"
Provides-Extra: docs
Requires-Dist: sphinx>=4.0.0; extra == "docs"
Requires-Dist: sphinx-rtd-theme>=1.0.0; extra == "docs"
